GunchuangdanXinlixueVol1/README.md
GunchuangdanXinlixueVol1/__init__.py
GunchuangdanXinlixueVol1/__main__.py
GunchuangdanXinlixueVol1/file.epub
GunchuangdanXinlixueVol1/index.html
GunchuangdanXinlixueVol1/css/__init__.py
GunchuangdanXinlixueVol1/css/annotations.css
GunchuangdanXinlixueVol1/css/main.css
GunchuangdanXinlixueVol1/css/normalize.css
GunchuangdanXinlixueVol1/css/popup.css
GunchuangdanXinlixueVol1/font/__init__.py
GunchuangdanXinlixueVol1/font/fontello.eot
GunchuangdanXinlixueVol1/font/fontello.svg
GunchuangdanXinlixueVol1/font/fontello.ttf
GunchuangdanXinlixueVol1/font/fontello.woff
GunchuangdanXinlixueVol1/img/__init__.py
GunchuangdanXinlixueVol1/img/annotator-glyph-sprite.png
GunchuangdanXinlixueVol1/img/annotator-icon-sprite.png
GunchuangdanXinlixueVol1/img/apple-touch-icon.png
GunchuangdanXinlixueVol1/img/cancelfullscreen.png
GunchuangdanXinlixueVol1/img/close.png
GunchuangdanXinlixueVol1/img/fullscreen.png
GunchuangdanXinlixueVol1/img/loader.gif
GunchuangdanXinlixueVol1/img/menu-icon.png
GunchuangdanXinlixueVol1/img/save.png
GunchuangdanXinlixueVol1/img/saved.png
GunchuangdanXinlixueVol1/img/settings-s.png
GunchuangdanXinlixueVol1/img/settings.png
GunchuangdanXinlixueVol1/img/star.png
GunchuangdanXinlixueVol1/js/__init__.py
GunchuangdanXinlixueVol1/js/epub.js
GunchuangdanXinlixueVol1/js/epub.min.js
GunchuangdanXinlixueVol1/js/epub.min.map
GunchuangdanXinlixueVol1/js/hooks.min.js
GunchuangdanXinlixueVol1/js/hooks.min.map
GunchuangdanXinlixueVol1/js/reader.js
GunchuangdanXinlixueVol1/js/reader.js.map
GunchuangdanXinlixueVol1/js/reader.min.js
GunchuangdanXinlixueVol1/js/reader.min.map
GunchuangdanXinlixueVol1/js/hooks/__init__.py
GunchuangdanXinlixueVol1/js/hooks/extensions/__init__.py
GunchuangdanXinlixueVol1/js/hooks/extensions/highlight.js
GunchuangdanXinlixueVol1/js/libs/__init__.py
GunchuangdanXinlixueVol1/js/libs/jquery.min.js
GunchuangdanXinlixueVol1/js/libs/localforage.min.js
GunchuangdanXinlixueVol1/js/libs/screenfull.js
gunchuangdan_xinlixue_vol1-2022.10.11.0.dist-info/METADATA
gunchuangdan_xinlixue_vol1-2022.10.11.0.dist-info/WHEEL
gunchuangdan_xinlixue_vol1-2022.10.11.0.dist-info/entry_points.txt
gunchuangdan_xinlixue_vol1-2022.10.11.0.dist-info/top_level.txt
gunchuangdan_xinlixue_vol1-2022.10.11.0.dist-info/RECORD
